nonebot_plugin_segbuilder-0.2.0.dist-info/METADATA
nonebot_plugin_segbuilder-0.2.0.dist-info/WHEEL
nonebot_plugin_segbuilder-0.2.0.dist-info/licenses/LICENSE
nonebot_plugin_segbuilder/__init__.py
nonebot_plugin_segbuilder/adapters/archive/kaiheila.py
nonebot_plugin_segbuilder/adapters/mirai2.py
nonebot_plugin_segbuilder/adapters/onebot_v11.py
nonebot_plugin_segbuilder/adapters/onebot_v12.py
nonebot_plugin_segbuilder/adapters/qqguild.py
nonebot_plugin_segbuilder/base.py
nonebot_plugin_segbuilder/utils.py
nonebot_plugin_segbuilder-0.2.0.dist-info/RECORD
