Metadata-Version: 2.1
Name: nonebot-plugin-segbuilder
Version: 0.2.0
Summary: 为不同的适配器提供更通用且简易的消息段构建方式
Author-Email: Well404 <well_404@outlook.com>
License: MIT
Requires-Python: >=3.8
Requires-Dist: anyio>=3.4.0
Requires-Dist: nonebot-adapter-onebot>=2.2.2
Requires-Dist: nonebot-adapter-qqguild>=0.2.1
Requires-Dist: nonebot-adapter-mirai2>=0.0.22
Requires-Dist: httpx>=0.20.0
Requires-Dist: nonebot2[fastapi,websockets]>=2.0.0rc4; extra == "dev"
Requires-Dist: pytest-asyncio>=0.21.0; extra == "dev"
Requires-Dist: nonebug>=0.3.3; extra == "dev"
Requires-Dist: pytest-mock>=3.10.0; extra == "dev"
Requires-Dist: pytest-cov>=4.0.0; extra == "dev"
Provides-Extra: dev
